geneity_oracle/__init__.py
geneity_oracle/batch_request_engine/__init__.py
geneity_oracle/batch_request_engine/batch_request_engine.py
geneity_oracle/batch_request_engine/oldest_out_cache.py
geneity_oracle/config/oracle_config.toml
geneity_oracle/config/oracle_users/sb_admin_dsn.toml
geneity_oracle/config/oracle_users/sportsbook_dsn.toml
geneity_oracle/config.py
geneity_oracle/const.py
geneity_oracle/errors.py
geneity_oracle/interface/__init__.py
geneity_oracle/interface/ora_async.py
geneity_oracle/interface/ora_base.py
geneity_oracle/interface/ora_sync.py
geneity_oracle/ora_types.py
geneity_oracle/query/__init__.py
geneity_oracle/query/execution.py
geneity_oracle/query/results.py
geneity_oracle/query/statement.py
geneity_oracle/settings.py
geneity_oracle/utils.py
geneity_oracle-0.2.6.dist-info/WHEEL
geneity_oracle-0.2.6.dist-info/METADATA
geneity_oracle-0.2.6.dist-info/RECORD
