Metadata-Version: 2.1
Name: geneity-oracle
Version: 0.2.6
Summary: Library for connections to oracle for geneity python3 apps
Author: Trading Bonus and Bet Team
Requires-Python: >=3.8,<4.0
Classifier: Programming Language :: Python :: 3
Classifier: Programming Language :: Python :: 3.10
Classifier: Programming Language :: Python :: 3.8
Classifier: Programming Language :: Python :: 3.9
Requires-Dist: cx-oracle (==8.0.1)
Requires-Dist: geneity-config (>=20.10.0)
Requires-Dist: geneity-logger (>=20.10.0)
Requires-Dist: toml (>=0.10.2,<0.11.0)
